tempy/__init__.py
tempy/__main__.py
tempy/bases.py
tempy/content.py
tempy/css.py
tempy/elements.py
tempy/exceptions.py
tempy/markdown.py
tempy/modifier.py
tempy/navigator.py
tempy/places.py
tempy/renderer.py
tempy/t.py
tempy/tags.py
tempy/tempy.py
tempy/tempyrepr.py
tempy/tools.py
tempy/widgets/__init__.py
tempy/widgets/tempylist.py
tempy/widgets/tempypage.py
tempy/widgets/tempytable.py
tem_py-1.5.3.dist-info/LICENSE
tem_py-1.5.3.dist-info/METADATA
tem_py-1.5.3.dist-info/WHEEL
tem_py-1.5.3.dist-info/top_level.txt
tem_py-1.5.3.dist-info/RECORD
