Metadata-Version: 2.1
Name: tem-py
Version: 1.5.3
Summary: Python OOP Templating System
Home-page: https://github.com/Hrabal/TemPy
Author: Federico Cerchiari
Author-email: federicocerchiari@gmail.com
License: APACHE 2.0
Platform: UNKNOWN
Classifier: License :: OSI Approved :: Apache Software License
Classifier: Programming Language :: Python
Classifier: Programming Language :: Python :: 3
Requires-Python: >=3.3
License-File: LICENSE
Requires-Dist: mistune
